jl2py/__init__.py
jl2py/__main__.py
jl2py/hello.py
jl2py/math.py
jl2py/math_utils.py
jl2py/sub_hello/__init__.py
jl2py/sub_hello/__main__.py
jl2py/sub_hello/hello.py
jl2py-0.0.1a1.dev1.dist-info/LICENSE
jl2py-0.0.1a1.dev1.dist-info/METADATA
jl2py-0.0.1a1.dev1.dist-info/WHEEL
jl2py-0.0.1a1.dev1.dist-info/top_level.txt
jl2py-0.0.1a1.dev1.dist-info/RECORD
