Metadata-Version: 2.2
Name: jl2py
Version: 0.0.1a1.dev1
Summary: Python Wrapper of the Julia Runtime
Author-email: Gennadi Ryan <gennadiryan@gmail.com>
Maintainer-email: Gennadi Ryan <gennadiryan@gmail.com>, Jack Champagne <jchampag@andrew.cmu.edu>
License: MIT License
Keywords: python,julia
Classifier: Development Status :: 3 - Alpha
Classifier: Intended Audience :: Developers
Classifier: Topic :: Software Development
Classifier: License :: OSI Approved :: MIT License
Classifier: Programming Language :: Python :: 3
Requires-Python: >=3.13
License-File: LICENSE
Requires-Dist: numpy>=2.2
Provides-Extra: tests
Requires-Dist: pytest>=8.3; extra == "tests"
